pymilestone/__init__.py
pymilestone/_caption_base.py
pymilestone/caption.py
pymilestone/category.py
pymilestone/element_type.py
pymilestone/milestone.py
pymilestone/milestoneplan.py
pymilestone/subcaption.py
pymilestone/task.py
pymilestone/util.py
pymilestone-1.0.0.dist-info/LICENSE
pymilestone-1.0.0.dist-info/METADATA
pymilestone-1.0.0.dist-info/WHEEL
pymilestone-1.0.0.dist-info/top_level.txt
pymilestone-1.0.0.dist-info/RECORD
