Metadata-Version: 2.1
Name: pymilestone
Version: 1.0.0
Summary: Package for creating a milestone plan with python using matplotlib.
Home-page: https://github.com/andprosoft/py_milestone
Author: Andriy Prots
Author-email: andprosoft@gmail.com
License: UNKNOWN
Platform: UNKNOWN
Classifier: Programming Language :: Python :: 3
Classifier: License :: OSI Approved :: GNU General Public License v3 (GPLv3)
Classifier: Operating System :: OS Independent
Requires-Python: >=3.6
License-File: LICENSE
Requires-Dist: matplotlib
Requires-Dist: python-dateutil
